AmazonProductScrapper/__init__.py
AmazonProductScrapper/product_data_keyword.py
AmazonProductScrapper/product_review_url.py
AmazonProductScrapper/methods/__init__.py
AmazonProductScrapper/methods/attributes.py
AmazonProductScrapper/methods/product_data.py
AmazonProductScrapper/methods/product_review_data.py
AmazonProductScrapper/methods/progress.py
AmazonProductScrapper/methods/review_attributes.py
AmazonProductScrapper/methods/soup.py
AmazonProductScrapper-2021.1.1.dist-info/METADATA
AmazonProductScrapper-2021.1.1.dist-info/WHEEL
AmazonProductScrapper-2021.1.1.dist-info/top_level.txt
AmazonProductScrapper-2021.1.1.dist-info/RECORD
