Metadata-Version: 2.1
Name: AmazonProductScrapper
Version: 2021.1.1
Summary: AmazonProductScrapper
Home-page: https://github.com/subhajit2001/AmazonProductScrapper
Author: Subhajit Saha
Author-email: subhajitsaha.formal@gmail.com
License: MIT
Keywords: python,Amazon Product Scrapper,Scrapper,Amazon,Product Scrapper
Platform: UNKNOWN
Classifier: Development Status :: 3 - Alpha
Classifier: Intended Audience :: Education
Classifier: Programming Language :: Python :: 3
Classifier: Programming Language :: Python :: 3.9
Classifier: Operating System :: MacOS :: MacOS X
Classifier: Operating System :: Microsoft :: Windows
Requires-Dist: pandas
Requires-Dist: requests
Requires-Dist: bs4
